{
  "SessionId": "24-10-2022 14:25:23",
  "DeviceType": "Bike",
  "Id": "Simulation",
  "MiniDatas": [
    {
      "Distance": 9,
      "Speed": 5,
      "Heartrate": 89,
      "Elapsed": 1
    },
    {
      "Distance": 15,
      "Speed": 6,
      "Heartrate": 90,
      "Elapsed": 2
    },
    {
      "Distance": 21,
      "Speed": 7,
      "Heartrate": 77,
      "Elapsed": 3
    },
    {
      "Distance": 29,
      "Speed": 7,
      "Heartrate": 64,
      "Elapsed": 5
    },
    {
      "Distance": 36,
      "Speed": 7,
      "Heartrate": 65,
      "Elapsed": 5
    },
    {
      "Distance": 43,
      "Speed": 8,
      "Heartrate": 86,
      "Elapsed": 6
    },
    {
      "Distance": 50,
      "Speed": 7,
      "Heartrate": 73,
      "Elapsed": 7
    },
    {
      "Distance": 59,
      "Speed": 6,
      "Heartrate": 74,
      "Elapsed": 9
    },
    {
      "Distance": 66,
      "Speed": 8,
      "Heartrate": 61,
      "Elapsed": 10
    },
    {
      "Distance": 73,
      "Speed": 7,
      "Heartrate": 82,
      "Elapsed": 10
    },
    {
      "Distance": 80,
      "Speed": 6,
      "Heartrate": 69,
      "Elapsed": 11
    },
    {
      "Distance": 90,
      "Speed": 8,
      "Heartrate": 70,
      "Elapsed": 13
    },
    {
      "Distance": 98,
      "Speed": 8,
      "Heartrate": 71,
      "Elapsed": 14
    },
    {
      "Distance": 105,
      "Speed": 7,
      "Heartrate": 98,
      "Elapsed": 14
    },
    {
      "Distance": 111,
      "Speed": 6,
      "Heartrate": 79,
      "Elapsed": 15
    },
    {
      "Distance": 119,
      "Speed": 6,
      "Heartrate": 72,
      "Elapsed": 17
    },
    {
      "Distance": 124,
      "Speed": 5,
      "Heartrate": 93,
      "Elapsed": 18
    },
    {
      "Distance": 129,
      "Speed": 5,
      "Heartrate": 94,
      "Elapsed": 19
    },
    {
      "Distance": 134,
      "Speed": 6,
      "Heartrate": 81,
      "Elapsed": 19
    },
    {
      "Distance": 142,
      "Speed": 5,
      "Heartrate": 83,
      "Elapsed": 21
    },
    {
      "Distance": 149,
      "Speed": 7,
      "Heartrate": 70,
      "Elapsed": 22
    },
    {
      "Distance": 155,
      "Speed": 7,
      "Heartrate": 90,
      "Elapsed": 23
    },
    {
      "Distance": 161,
      "Speed": 6,
      "Heartrate": 77,
      "Elapsed": 23
    },
    {
      "Distance": 168,
      "Speed": 5,
      "Heartrate": 78,
      "Elapsed": 25
    },
    {
      "Distance": 172,
      "Speed": 5,
      "Heartrate": 65,
      "Elapsed": 26
    },
    {
      "Distance": 177,
      "Speed": 5,
      "Heartrate": 86,
      "Elapsed": 27
    },
    {
      "Distance": 182,
      "Speed": 5,
      "Heartrate": 73,
      "Elapsed": 27
    },
    {
      "Distance": 189,
      "Speed": 6,
      "Heartrate": 74,
      "Elapsed": 29
    },
    {
      "Distance": 195,
      "Speed": 6,
      "Heartrate": 61,
      "Elapsed": 30
    },
    {
      "Distance": 201,
      "Speed": 5,
      "Heartrate": 88,
      "Elapsed": 31
    },
    {
      "Distance": 206,
      "Speed": 6,
      "Heartrate": 90,
      "Elapsed": 32
    },
    {
      "Distance": 213,
      "Speed": 6,
      "Heartrate": 77,
      "Elapsed": 33
    },
    {
      "Distance": 218,
      "Speed": 5,
      "Heartrate": 97,
      "Elapsed": 34
    },
    {
      "Distance": 223,
      "Speed": 5,
      "Heartrate": 84,
      "Elapsed": 35
    },
    {
      "Distance": 229,
      "Speed": 5,
      "Heartrate": 71,
      "Elapsed": 36
    }
  ]
}