{
  "id": "tunnel/send",
  "data": {
    "id": "8b8da7f2-2049-4f4d-abc5-996337f1683a",
    "data": {
      "data": [
        {
          "children": [
            {
              "components": [
                {
                  "position": [
                    0.0,
                    120,
                    0.0
                  ],
                  "rotation": [
                    0.0,
                    0.70710676908493,
                    0.0,
                    0.70710676908493
                  ],
                  "scale": [
                    10,
                    10,
                    10
                  ],
                  "type": "transform"
                },
                {
                  "type": "camera",
                  "useFbo": false
                },
                {
                  "light": "a74c7fbe-f05d-4a60-93d1-03f706fa9235",
                  "timeOfDay": 10.5,
                  "type": "dynamicskybox"
                }
              ],
              "name": "Camera",
              "uuid": "b18ea31b-948a-4c99-9572-b17a6d221561"
            },
            {
              "components": [
                {
                  "position": [
                    0.0,
                    135,
                    0.00048828125
                  ],
                  "rotation": [
                    0.0,
                    -0.0397779010236263,
                    0.0,
                    0.565381824970245
                  ],
                  "scale": [
                    0.0,
                    0.0,
                    0.0
                  ],
                  "type": "transform"
                },
                {
                  "attach": "MainUserHead",
                  "type": "transformattach"
                }
              ],
              "name": "Head",
              "uuid": "f98a2896-7158-422b-a06a-a9da673833ab"
            }
          ],
          "components": [
            {
              "position": [
                50,
                1,
                20
              ],
              "rotation": [
                0.0,
                -0.851408839225769,
                0.0,
                0.524502635002136
              ],
              "scale": [
                0.00999999977648258,
                0.00999999977648258,
                0.00999999977648258
              ],
              "type": "transform"
            },
            {
              "castShadow": true,
              "cullBackFaces": true,
              "file": "data/NetworkEngine/models/bike/bike_anim.fbx",
              "type": "animatedmodelrenderer"
            }
          ],
          "name": "Bike",
          "uuid": "65a7cb7c-2ce6-460f-bd8f-abca27cc99ce"
        }
      ],
      "id": "scene/node/find",
      "serial": "9",
      "status": "ok"
    }
  }
}